LICENSE
MANIFEST.in
README.rst
VERSION
setup.py
tests.py
docs/changelog.rst
docs/index.rst
docs/melddict.rst
docs/readme.rst
melddict/__init__.py
melddict.egg-info/PKG-INFO
melddict.egg-info/SOURCES.txt
melddict.egg-info/dependency_links.txt
melddict.egg-info/top_level.txt