Metadata-Version: 1.1
Name: melddict
Version: 1.0.1
Summary: Dictionary with recursive additive and subtractive merging
Home-page: https://github.com/johnsca/melddict
Author: Cory Johns
Author-email: johnsca@gmail.com
License: Apache 2
Platform: UNKNOWN
Classifier: Development Status :: 5 - Production/Stable
Classifier: Intended Audience :: Developers
Classifier: Programming Language :: Python
Classifier: Programming Language :: Python :: 3
Classifier: Programming Language :: Python :: 3.5
